fundrives/__init__.py
fundrives/aliopen/__init__.py
fundrives/aliopen/auth.py
fundrives/aliopen/drive.py
fundrive_alipan-1.3.12.dist-info/METADATA
fundrive_alipan-1.3.12.dist-info/WHEEL
fundrive_alipan-1.3.12.dist-info/top_level.txt
fundrive_alipan-1.3.12.dist-info/RECORD
