Metadata-Version: 2.4
Name: fundrive-alipan
Version: 1.3.12
Summary: fundrive-alipan
Author-email: 牛哥 <niuliangtao@qq.com>, farfarfun <farfarfun@qq.com>
Maintainer-email: 牛哥 <niuliangtao@qq.com>, farfarfun <farfarfun@qq.com>
Project-URL: Organization, https://github.com/farfarfun
Project-URL: Repository, https://github.com/farfarfun/fundrive-alipan
Project-URL: Releases, https://github.com/farfarfun/fundrive-alipan/releases
Requires-Python: >=3.7
Requires-Dist: funget>=1.0.45
Requires-Dist: funutil>=1.0.19
Requires-Dist: qrcode>=7.4.2
